COPYING
MANIFEST.in
README.md
setup.py
debian/changelog
debian/compat
debian/control
debian/copyright
debian/python-execo.lintian-overrides
debian/rules
doc/apidoc.rst
doc/conf.py
doc/execo.png
doc/execo.rst
doc/execo_engine.rst
doc/execo_g5k.rst
doc/faq.rst
doc/index.rst
doc/misc.rst
doc/python2-python3.rst
doc/readme.rst
doc/userguide.rst
doc/code_samples/g5k_chainput_perf.py
doc/code_samples/g5k_check_cluster_cpu.py
doc/code_samples/g5k_iperf.py
doc/code_samples/g5k_taktuk_perf.py
doc/code_samples/g5k_tcp_congestion.png
doc/code_samples/g5k_tcp_congestion.py
doc/code_samples/g5k_tcp_congestion_process_results.py
doc/code_samples/g5k_tcptrace.py
doc/code_samples/g5k_xp_graph.png
doc/code_samples/g5k_xp_graph.py
src/execo/__init__.py
src/execo/_version.py
src/execo/action.py
src/execo/conductor.py
src/execo/config.py
src/execo/exception.py
src/execo/execo-chainput
src/execo/host.py
src/execo/log.py
src/execo/process.py
src/execo/report.py
src/execo/ssh_utils.py
src/execo/substitutions.py
src/execo/time_utils.py
src/execo/utils.py
src/execo.egg-info/PKG-INFO
src/execo.egg-info/SOURCES.txt
src/execo.egg-info/dependency_links.txt
src/execo.egg-info/top_level.txt
src/execo_engine/__init__.py
src/execo_engine/engine.py
src/execo_engine/log.py
src/execo_engine/sweep.py
src/execo_engine/utils.py
src/execo_g5k/__init__.py
src/execo_g5k/api_utils.py
src/execo_g5k/charter.py
src/execo_g5k/config.py
src/execo_g5k/kadeploy.py
src/execo_g5k/oar.py
src/execo_g5k/planning.py
src/execo_g5k/topology.py
src/execo_g5k/utils.py