Metadata-Version: 2.1
Name: execo
Version: 2.8.2
Summary: Python API for asynchronous control of local or remote, standalone or parallel, unix processes.
Home-page: https://gitlab.inria.fr/mimbert/execo
Author: Matthieu Imbert
Author-email: matthieu.imbert@inria.fr
License: GNU GPL v3
Platform: unix
Classifier: Development Status :: 4 - Beta
Classifier: Environment :: Console
Classifier: Intended Audience :: Developers
Classifier: Intended Audience :: Information Technology
Classifier: Intended Audience :: Science/Research
Classifier: Intended Audience :: System Administrators
Classifier: Operating System :: POSIX :: Linux
Classifier: Programming Language :: Python :: 2.6
Classifier: Programming Language :: Python :: 2.7
Classifier: Programming Language :: Python :: 3.8
Classifier: Topic :: Software Development
Classifier: Topic :: System :: Clustering
Classifier: Topic :: System :: Distributed Computing
